aim_guardrails/__init__.py
aim_guardrails/exceptions.py
aim_guardrails/guardrails.py
aim_guardrails/utils.py
aim_guardrails-0.1.2.dist-info/METADATA
aim_guardrails-0.1.2.dist-info/WHEEL
aim_guardrails-0.1.2.dist-info/RECORD
