Metadata-Version: 2.3
Name: aim-guardrails
Version: 0.1.2
Summary: Aim Security Guardrails for OpenAI Agents
Author: Aim Security
Requires-Python: >=3.10
Classifier: Programming Language :: Python :: 3
Classifier: Programming Language :: Python :: 3.10
Classifier: Programming Language :: Python :: 3.11
Classifier: Programming Language :: Python :: 3.12
Classifier: Programming Language :: Python :: 3.13
Requires-Dist: httpx (>=0.24.0)
Requires-Dist: openai (>=1.0.0)
Requires-Dist: openai-agents (>=0.0.3,<0.0.4)
Requires-Dist: pydantic (>=2.0.0)
Project-URL: Repository, https://github.com/yourusername/aim-guardrails
